geventhttpclient/__init__.py
geventhttpclient/_parser.cpython-310-powerpc64le-linux-gnu.so
geventhttpclient/api.py
geventhttpclient/client.py
geventhttpclient/connectionpool.py
geventhttpclient/header.py
geventhttpclient/httplib.py
geventhttpclient/httplib2.py
geventhttpclient/requests.py
geventhttpclient/response.py
geventhttpclient/url.py
geventhttpclient/useragent.py
geventhttpclient-2.3.6.dist-info/METADATA
geventhttpclient-2.3.6.dist-info/WHEEL
geventhttpclient-2.3.6.dist-info/top_level.txt
geventhttpclient-2.3.6.dist-info/RECORD
geventhttpclient-2.3.6.dist-info/licenses/LICENSE-MIT
