Metadata-Version: 2.4
Name: geventhttpclient
Version: 2.3.6
Summary: HTTP client library for gevent
Author-email: Antonin Amand <antonin.amand@gmail.com>
License-Expression: MIT
Project-URL: homepage, http://github.com/geventhttpclient/geventhttpclient
Project-URL: issues, http://github.com/geventhttpclient/geventhttpclient/issues
Project-URL: download, https://pypi.org/project/geventhttpclient/#files
Keywords: http,gevent,client
Classifier: Development Status :: 5 - Production/Stable
Classifier: Intended Audience :: Developers
Classifier: Intended Audience :: Information Technology
Classifier: Operating System :: OS Independent
Classifier: Programming Language :: Python :: 3
Classifier: Programming Language :: Python :: 3.9
Classifier: Programming Language :: Python :: 3.10
Classifier: Programming Language :: Python :: 3.11
Classifier: Programming Language :: Python :: 3.12
Classifier: Programming Language :: Python :: 3.13
Classifier: Programming Language :: Python :: 3.14
Classifier: Programming Language :: Python :: 3 :: Only
Classifier: Topic :: Software Development :: Libraries
Requires-Python: >=3.9
License-File: LICENSE-MIT
Requires-Dist: gevent
Requires-Dist: certifi
Requires-Dist: brotli
Requires-Dist: urllib3
Provides-Extra: dev
Requires-Dist: pytest; extra == "dev"
Requires-Dist: dpkt; extra == "dev"
Requires-Dist: requests; extra == "dev"
Provides-Extra: benchmarks
Requires-Dist: requests; extra == "benchmarks"
Requires-Dist: httpx; extra == "benchmarks"
Requires-Dist: urllib3; extra == "benchmarks"
Requires-Dist: httplib2; extra == "benchmarks"
Provides-Extra: examples
Requires-Dist: oauth2; extra == "examples"
Dynamic: license-file
